observabilipy/__init__.py
observabilipy/py.typed
observabilipy/adapters/__init__.py
observabilipy/adapters/events.py
observabilipy/adapters/logging.py
observabilipy/adapters/logging_context.py
observabilipy/adapters/frameworks/__init__.py
observabilipy/adapters/frameworks/asgi.py
observabilipy/adapters/frameworks/django.py
observabilipy/adapters/frameworks/fastapi.py
observabilipy/adapters/frameworks/wsgi.py
observabilipy/adapters/storage/__init__.py
observabilipy/adapters/storage/async_sync.py
observabilipy/adapters/storage/in_memory.py
observabilipy/adapters/storage/ring_buffer.py
observabilipy/adapters/storage/sqlite_base.py
observabilipy/adapters/storage/sqlite_logs.py
observabilipy/adapters/storage/sqlite_metrics.py
observabilipy/core/__init__.py
observabilipy/core/exceptions.py
observabilipy/core/instrument.py
observabilipy/core/logs.py
observabilipy/core/metrics.py
observabilipy/core/models.py
observabilipy/core/ports.py
observabilipy/core/retention.py
observabilipy/core/services.py
observabilipy/core/encoding/__init__.py
observabilipy/core/encoding/ndjson.py
observabilipy/core/encoding/prometheus.py
observabilipy/core/events/__init__.py
observabilipy/core/events/models.py
observabilipy/core/events/registry.py
observabilipy/runtime/__init__.py
observabilipy/runtime/embedded.py
observabilipy-1.4.0.dist-info/METADATA
observabilipy-1.4.0.dist-info/WHEEL
observabilipy-1.4.0.dist-info/licenses/LICENSE
observabilipy-1.4.0.dist-info/RECORD
