Metadata-Version: 2.4
Name: observabilipy
Version: 1.4.0
Summary: Framework-agnostic metrics and structured log collection with hexagonal architecture
Project-URL: Homepage, https://github.com/PhilHem/observabilipy
Project-URL: Repository, https://github.com/PhilHem/observabilipy
Project-URL: Issues, https://github.com/PhilHem/observabilipy/issues
Author-email: PhilHem <34508934+PhilHem@users.noreply.github.com>
License-Expression: MIT
License-File: LICENSE
Keywords: django,fastapi,grafana,logging,metrics,observability,prometheus
Classifier: Development Status :: 4 - Beta
Classifier: Framework :: Django
Classifier: Framework :: FastAPI
Classifier: Intended Audience :: Developers
Classifier: License :: OSI Approved :: MIT License
Classifier: Programming Language :: Python :: 3
Classifier: Programming Language :: Python :: 3.13
Classifier: Topic :: System :: Logging
Classifier: Topic :: System :: Monitoring
Classifier: Typing :: Typed
Requires-Python: >=3.13
Requires-Dist: aiosqlite>=0.21.0
Provides-Extra: django
Requires-Dist: django>=4.2; extra == 'django'
Provides-Extra: examples
Requires-Dist: fastapi>=0.124.2; extra == 'examples'
Requires-Dist: psutil>=5.9.0; extra == 'examples'
Provides-Extra: fastapi
Requires-Dist: fastapi>=0.124.2; extra == 'fastapi'
